logbatcher/additional_cluster.py
logbatcher/cluster.py
logbatcher/matching.py
logbatcher/parser.py
logbatcher/parsing_base.py
logbatcher/postprocess.py
logbatcher/sample.py
logbatcher/util.py
logbatcher-0.1.1.dist-info/LICENSE
logbatcher-0.1.1.dist-info/METADATA
logbatcher-0.1.1.dist-info/WHEEL
logbatcher-0.1.1.dist-info/top_level.txt
logbatcher-0.1.1.dist-info/RECORD
