Metadata-Version: 2.1
Name: logbatcher
Version: 0.1.1
Summary: A tool for batch parsing of log files
License-File: LICENSE
Requires-Dist: httpx >=0.27.2
Requires-Dist: natsort >=8.4.0
Requires-Dist: nltk >=3.9.1
Requires-Dist: numpy >=1.24.4
Requires-Dist: openai >=1.42.0
Requires-Dist: pandas >=2.0.3
Requires-Dist: regex >=2024.7.24
Requires-Dist: scikit-learn >=1.3.2
Requires-Dist: scipy >=1.13.1
Requires-Dist: setuptools >=72.1.0
Requires-Dist: tenacity >=9.0.0
Requires-Dist: tiktoken >=0.7.0
Requires-Dist: together >=1.2.9
Requires-Dist: tqdm >=4.66.5
